{
  "anvil_cost": 4,
  "description": {
    "translate": "enchantment.tolkienmobs.hobbit_plow_key"
  },
  "effects": {
    "tolkienmobs:use_on_block": [
      {
        "effect": {
          "type": "tolkienmobs:hobbit_plow",
          "level": 1
        }
      }
    ]
  },
  "exclusive_set": "#minecraft:exclusive_set/mining",
  "max_cost": {
    "base": 25,
    "per_level_above_first": 10
  },
  "max_level": 1,
  "min_cost": {
    "base": 10,
    "per_level_above_first": 10
  },
  "slots": [
    "mainhand"
  ],
  "supported_items": "#minecraft:hoes",
  "weight": 1
}